{
    "metadata": {
        "data_version": "5",
        "match_id": "NA1_5022391485",
        "participants": [
            "Pc0NTLNPwa8Jn99PEPusu28o3c9B2OJpp__qYUqUOAz--eEFaSfBK9TVYFl_TQHOEDhzdZ_iJqIPbQ",
            "H_DsBPAhuu5sICzJmDcTeYSHStom1W1lHgm56_9br-8rgdFYzUUajLoMlUyaK9b-Qck660Ecy0YSBw",
            "m-bovi9SPQCshfROPP4uUboETgsz_pfvW6-QMcaDmwt1E3ar2WNpKZLrdmBC5qE7EOZIrXfWaMTZkQ",
            "e6MwbRy8zeEa7ihcHQ5tQvnKybF8BPIe18RojXrfiouvf4gV7PLOxCMleSmka6KCizKED4mdL4tDMg",
            "IqrC2L86g3O7fcWP3KBTEScZHJ42eJ-VvP--E8TY_FinN9gLnpqICExBByu_n1m1_meJ8s6skUTRcg",
            "EOxDWPkVxvgjKJ1VBgvGgPMLyjbjH_9muNVdSnpq4OTztRIASrt1VmjPkl0PeASCfcquMsLbbzYnVA",
            "nePyy7qsdK0irJsw3eKwUUQc20aO7dT1xviOAKO0tbxe27kP2PdQ0HbLaEGT6rK-Ehe5OIM7ujhOCw",
            "6riTyikRSA7KuuFVS6fdpTzT_wkHz7ZVO2jXiob2D_S0bI54zkN6EJUb8b10ESMb-p2SUV4L73yd3g"
        ]
    },
    "info": {
        "endOfGameResult": "GameComplete",
        "gameCreation": 1718702162000,
        "gameId": 5022391485,
        "game_datetime": 1718704371323,
        "game_length": 2182.826904296875,
        "game_version": "Linux Version 14.12.594.4901 (Jun 13 2024/17:32:07) [PUBLIC] <Releases/14.12>",
        "mapId": 22,
        "participants": [
            {
                "augments": [
                    "TFT11_Augment_DuelistCrest",
                    "TFT9_Augment_ArmyBuilding",
                    "TFT6_Augment_PortableForge"
                ],
                "companion": {
                    "content_ID": "a8cca427-0ee2-45e2-8b06-4019cdd0757d",
                    "item_ID": 5001,
                    "skin_ID": 1,
                    "species": "PetMiniGolem"
                },
                "gold_left": 0,
                "last_round": 31,
                "level": 8,
                "missions": {
                    "PlayerScore2": 90
                },
                "placement": 7,
                "players_eliminated": 0,
                "puuid": "Pc0NTLNPwa8Jn99PEPusu28o3c9B2OJpp__qYUqUOAz--eEFaSfBK9TVYFl_TQHOEDhzdZ_iJqIPbQ",
                "time_eliminated": 1806.962158203125,
                "total_damage_to_players": 82,
                "traits": [
                    {
                        "name": "TFT11_Dragonlord",
                        "num_units": 2,
                        "style": 1,
                        "tier_current": 1,
                        "tier_total": 4
                    },
                    {
                        "name": "TFT11_Duelist",
                        "num_units": 8,
                        "style": 3,
                        "tier_current": 4,
                        "tier_total": 4
                    },
                    {
                        "name": "TFT11_Fated",
                        "num_units": 1,
                        "style": 0,
                        "tier_current": 0,
                        "tier_total": 4
                    },
                    {
                        "name": "TFT11_Fortune",
                        "num_units": 1,
                        "style": 0,
                        "tier_current": 0,
                        "tier_total": 3
                    },
                    {
                        "name": "TFT11_Heavenly",
                        "num_units": 1,
                        "style": 0,
                        "tier_current": 0,
                        "tier_total": 6
                    },
                    {
                        "name": "TFT11_InkShadow",
                        "num_units": 1,
                        "style": 0,
                        "tier_current": 0,
                        "tier_total": 3
                    },
                    {
                        "name": "TFT11_Sage",
                        "num_units": 1,
                        "style": 0,
                        "tier_current": 0,
                        "tier_total": 4
                    },
                    {
                        "name": "TFT11_Storyweaver",
                        "num_units": 1,
                        "style": 0,
                        "tier_current": 0,
                        "tier_total": 4
                    },
                    {
                        "name": "TFT11_Umbral",
                        "num_units": 1,
                        "style": 0,
                        "tier_current": 0,
                        "tier_total": 4
                    }
                ],
                "units": [
                    {
                        "character_id": "TFT11_Darius",
                        "itemNames": [],
                        "name": "",
                        "rarity": 0,
                        "tier": 2
                    },
                    {
                        "character_id": "TFT11_Yasuo",
                        "itemNames": [],
                        "name": "",
                        "rarity": 0,
                        "tier": 2
                    },
                    {
                        "character_id": "TFT11_Qiyana",
                        "itemNames": [],
                        "name": "",
                        "rarity": 1,
                        "tier": 2
                    },
                    {
                        "character_id": "TFT11_Diana",
                        "itemNames": [
                            "TFT11_Item_ChallengerEmblemItem"
                        ],
                        "name": "",
                        "rarity": 2,
                        "tier": 2
                    },
                    {
                        "character_id": "TFT11_Tristana",
                        "itemNames": [
                            "TFT_Item_LastWhisper",
                            "TFT_Item_Artifact_RapidFirecannon"
                        ],
                        "name": "",
                        "rarity": 2,
                        "tier": 3
                    },
                    {
                        "character_id": "TFT11_Volibear",
                        "itemNames": [],
                        "name": "",
                        "rarity": 2,
                        "tier": 2
                    },
                    {
                        "character_id": "TFT11_LeeSin",
                        "itemNames": [
                            "TFT_Item_SteraksGage",
                            "TFT_Item_Bloodthirster",
                            "TFT_Item_TitansResolve"
                        ],
                        "name": "",
                        "rarity": 4,
                        "tier": 2
                    },
                    {
                        "character_id": "TFT11_Irelia",
                        "itemNames": [
                            "TFT_Item_GuinsoosRageblade",
                            "TFT_Item_MadredsBloodrazor"
                        ],
                        "name": "",
                        "rarity": 6,
                        "tier": 1
                    }
                ]
            },
            {
                "augments": [
                    "TFT11_Augment_NeekoCarry",
                    "TFT7_Augment_BandOfThieves1",
                    "TFT11_Augment_Reinfourcement"
                ],
                "companion": {
                    "content_ID": "816f170e-1aab-4af4-a7d2-d161e21cb8ea",
                    "item_ID": 25003,
                    "skin_ID": 3,
                    "species": "PetAoShin"
                },
                "gold_left": 60,
                "last_round": 27,
                "level": 8,
                "missions": {
                    "PlayerScore2": 79
                },
                "placement": 8,
                "players_eliminated": 0,
                "puuid": "H_DsBPAhuu5sICzJmDcTeYSHStom1W1lHgm56_9br-8rgdFYzUUajLoMlUyaK9b-Qck660Ecy0YSBw",
                "time_eliminated": 1582.95751953125,
                "total_damage_to_players": 45,
                "traits": [
                    {
                        "name": "TFT11_Arcanist",
                        "num_units": 1,
                        "style": 0,
                        "tier_current": 0,
                        "tier_total": 4
                    },
                    {
                        "name": "TFT11_Behemoth",
                        "num_units": 2,
                        "style": 1,
                        "tier_current": 1,
                        "tier_total": 3
                    },
                    {
                        "name": "TFT11_Bruiser",
                        "num_units": 1,
                        "style": 0,
                        "tier_current": 0,
                        "tier_total": 4
                    },
                    {
                        "name": "TFT11_Fated",
                        "num_units": 1,
                        "style": 0,
                        "tier_current": 0,
                        "tier_total": 4
                    },
                    {
                        "name": "TFT11_Great",
                        "num_units": 1,
                        "style": 5,
                        "tier_current": 1,
                        "tier_total": 1
                    },
                    {
                        "name": "TFT11_Heavenly",
                        "num_units": 2,
                        "style": 1,
                        "tier_current": 1,
                        "tier_total": 6
                    },
                    {
                        "name": "TFT11_InkShadow",
                        "num_units": 1,
                        "style": 0,
                        "tier_current": 0,
                        "tier_total": 3
                    },
                    {
                        "name": "TFT11_Invoker",
                        "num_units": 2,
                        "style": 1,
                        "tier_current": 1,
                        "tier_total": 3
                    },
                    {
                        "name": "TFT11_Mythic",
                        "num_units": 5,
                        "style": 2,
                        "tier_current": 2,
                        "tier_total": 4
                    },
                    {
                        "name": "TFT11_Sage",
                        "num_units": 1,
                        "style": 0,
                        "tier_current": 0,
                        "tier_total": 4
                    },
                    {
                        "name": "TFT11_Sniper",
                        "num_units": 1,
                        "style": 0,
                        "tier_current": 0,
                        "tier_total": 3
                    },
                    {
                        "name": "TFT11_SpiritWalker",
                        "num_units": 1,
                        "style": 5,
                        "tier_current": 1,
                        "tier_total": 1
                    },
                    {
                        "name": "TFT11_Umbral",
                        "num_units": 1,
                        "style": 0,
                        "tier_current": 0,
                        "tier_total": 4
                    },
                    {
                        "name": "TFT11_Warden",
                        "num_units": 1,
                        "style": 0,
                        "tier_current": 0,
                        "tier_total": 3
                    }
                ],
                "units": [
                    {
                        "character_id": "TFT11_KogMaw",
                        "itemNames": [],
                        "name": "",
                        "rarity": 0,
                        "tier": 2
                    },
                    {
                        "character_id": "TFT11_ChoGath",
                        "itemNames": [],
                        "name": "",
                        "rarity": 0,
                        "tier": 2
                    },
                    {
                        "character_id": "TFT11_Neeko",
                        "itemNames": [
                            "TFT_Item_ArchangelsStaff",
                            "TFT_Item_Bloodthirster"
                        ],
                        "name": "",
                        "rarity": 1,
                        "tier": 2
                    },
                    {
                        "character_id": "TFT11_TahmKench",
                        "itemNames": [
                            "TFT_Item_SpectralGauntlet",
                            "TFT_Item_GargoyleStoneplate"
                        ],
                        "name": "",
                        "rarity": 2,
                        "tier": 1
                    },
                    {
                        "character_id": "TFT11_Lillia",
                        "itemNames": [
                            "TFT_Item_SpearOfShojin",
                            "TFT_Item_JeweledGauntlet"
                        ],
                        "name": "",
                        "rarity": 4,
                        "tier": 2
                    },
                    {
                        "character_id": "TFT11_Sett",
                        "itemNames": [],
                        "name": "",
                        "rarity": 6,
                        "tier": 1
                    },
                    {
                        "character_id": "TFT11_WuKong",
                        "itemNames": [
                            "TFT_Item_ThiefsGloves",
                            "TFT_Item_NightHarvester",
                            "TFT_Item_RabadonsDeathcap"
                        ],
                        "name": "",
                        "rarity": 6,
                        "tier": 1
                    },
                    {
                        "character_id": "TFT11_Udyr",
                        "itemNames": [],
                        "name": "",
                        "rarity": 6,
                        "tier": 1
                    }
                ]
            },
            {
                "augments": [
                    "TFT6_Augment_TradeSector",
                    "TFT11_Augment_GoldenRemover",
                    "TFT6_Augment_PortableForge"
                ],
                "companion": {
                    "content_ID": "ca9f7611-cc7d-437d-87db-9983166f794c",
                    "item_ID": 6026,
                    "skin_ID": 26,
                    "species": "PetPenguKnight"
                },
                "gold_left": 2,
                "last_round": 38,
                "level": 9,
                "missions": {
                    "PlayerScore2": 217
                },
                "placement": 1,
                "players_eliminated": 4,
                "puuid": "m-bovi9SPQCshfROPP4uUboETgsz_pfvW6-QMcaDmwt1E3ar2WNpKZLrdmBC5qE7EOZIrXfWaMTZkQ",
                "time_eliminated": 2174.625732421875,
                "total_damage_to_players": 160,
                "traits": [
                    {
                        "name": "TFT11_Altruist",
                        "num_units": 2,
                        "style": 1,
                        "tier_current": 1,
                        "tier_total": 3
                    },
                    {
                        "name": "TFT11_Arcanist",
                        "num_units": 1,
                        "style": 0,
                        "tier_current": 0,
                        "tier_total": 4
                    },
                    {
                        "name": "TFT11_Bruiser",
                        "num_units": 2,
                        "style": 1,
                        "tier_current": 1,
                        "tier_total": 4
                    },
                    {
                        "name": "TFT11_Dragonlord",
                        "num_units": 2,
                        "style": 1,
                        "tier_current": 1,
                        "tier_total": 4
                    },
                    {
                        "name": "TFT11_Duelist",
                        "num_units": 2,
                        "style": 1,
                        "tier_current": 1,
                        "tier_total": 4
                    },
                    {
                        "name": "TFT11_Exalted",
                        "num_units": 1,
                        "style": 0,
                        "tier_current": 0,
                        "tier_total": 2
                    },
                    {
                        "name": "TFT11_Fortune",
                        "num_units": 1,
                        "style": 0,
                        "tier_current": 0,
                        "tier_total": 3
                    },
                    {
                        "name": "TFT11_Lovers",
                        "num_units": 1,
                        "style": 5,
                        "tier_current": 1,
                        "tier_total": 1
                    },
                    {
                        "name": "TFT11_Sage",
                        "num_units": 1,
                        "style": 0,
                        "tier_current": 0,
                        "tier_total": 4
                    },
                    {
                        "name": "TFT11_Storyweaver",
                        "num_units": 7,
                        "style": 3,
                        "tier_current": 3,
                        "tier_total": 4
                    },
                    {
                        "name": "TFT11_Trickshot",
                        "num_units": 1,
                        "style": 0,
                        "tier_current": 0,
                        "tier_total": 2
                    },
                    {
                        "name": "TFT11_Warden",
                        "num_units": 1,
                        "style": 0,
                        "tier_current": 0,
                        "tier_total": 3
                    }
                ],
                "units": [
                    {
                        "character_id": "TFT11_Sivir",
                        "itemNames": [],
                        "name": "",
                        "rarity": 0,
                        "tier": 1
                    },
                    {
                        "character_id": "TFT11_Garen",
                        "itemNames": [],
                        "name": "",
                        "rarity": 0,
                        "tier": 2
                    },
                    {
                        "character_id": "TFT11_Zyra",
                        "itemNames": [],
                        "name": "",
                        "rarity": 1,
                        "tier": 2
                    },
                    {
                        "character_id": "TFT11_Riven",
                        "itemNames": [],
                        "name": "",
                        "rarity": 1,
                        "tier": 2
                    },
                    {
                        "character_id": "TFT11_Zoe",
                        "itemNames": [
                            "TFT_Item_ArchangelsStaff",
                            "TFT_Item_NeedlesslyLargeRod",
                            "TFT_Item_RabadonsDeathcap"
                        ],
                        "name": "",
                        "rarity": 2,
                        "tier": 2
                    },
                    {
                        "character_id": "TFT11_LeeSin",
                        "itemNames": [
                            "TFT_Item_UnstableConcoction",
                            "TFT_Item_Bloodthirster",
                            "TFT_Item_MadredsBloodrazor"
                        ],
                        "name": "",
                        "rarity": 4,
                        "tier": 2
                    },
                    {
                        "character_id": "TFT11_Galio",
                        "itemNames": [
                            "TFT_Item_SpectralGauntlet",
                            "TFT_Item_DragonsClaw",
                            "TFT_Item_RedBuff"
                        ],
                        "name": "",
                        "rarity": 4,
                        "tier": 2
                    },
                    {
                        "character_id": "TFT11_Rakan",
                        "itemNames": [],
                        "name": "",
                        "rarity": 6,
                        "tier": 1
                    },
                    {
                        "character_id": "TFT11_Irelia",
                        "itemNames": [
                            "TFT9_Item_OrnnHorizonFocus",
                            "TFT_Item_InfinityEdge",
                            "TFT_Item_GuinsoosRageblade"
                        ],
                        "name": "",
                        "rarity": 6,
                        "tier": 2
                    },
                    {
                        "character_id": "TFT11_Kayle",
                        "itemNames": [
                            "TFT11_Storyweaver7_AP",
                            "TFT11_Storyweaver5_AP",
                            "TFT11_Storyweaver3_AP"
                        ],
                        "name": "",
                        "rarity": 9,
                        "tier": 3
                    }
                ]
            },
            {
                "augments": [
                    "TFT6_Augment_Diversify2",
                    "TFT9_Augment_YoungAndWildAndFree",
                    "TFT11_Augment_Warden"
                ],
                "companion": {
                    "content_ID": "4e79c791-2fc8-4b46-a3e3-6271c7142f8b",
                    "item_ID": 15040,
                    "skin_ID": 40,
                    "species": "PetSennaBunny"
                },
                "gold_left": 30,
                "last_round": 33,
                "level": 8,
                "missions": {
                    "PlayerScore2": 95
                },
                "placement": 6,
                "players_eliminated": 0,
                "puuid": "e6MwbRy8zeEa7ihcHQ5tQvnKybF8BPIe18RojXrfiouvf4gV7PLOxCMleSmka6KCizKED4mdL4tDMg",
                "time_eliminated": 1908.9085693359375,
                "total_damage_to_players": 109,
                "traits": [
                    {
                        "name": "TFT11_Arcanist",
                        "num_units": 1,
                        "style": 0,
                        "tier_current": 0,
                        "tier_total": 4
                    },
                    {
                        "name": "TFT11_Fated",
                        "num_units": 1,
                        "style": 0,
                        "tier_current": 0,
                        "tier_total": 4
                    },
                    {
                        "name": "TFT11_Ghostly",
                        "num_units": 2,
                        "style": 1,
                        "tier_current": 1,
                        "tier_total": 4
                    },
                    {
                        "name": "TFT11_InkShadow",
                        "num_units": 2,
                        "style": 0,
                        "tier_current": 0,
                        "tier_total": 3
                    },
                    {
                        "name": "TFT11_Mythic",
                        "num_units": 1,
                        "style": 0,
                        "tier_current": 0,
                        "tier_total": 4
                    },
                    {
                        "name": "TFT11_Porcelain",
                        "num_units": 2,
                        "style": 1,
                        "tier_current": 1,
                        "tier_total": 3
                    },
                    {
                        "name": "TFT11_Sniper",
                        "num_units": 4,
                        "style": 2,
                        "tier_current": 2,
                        "tier_total": 3
                    },
                    {
                        "name": "TFT11_Warden",
                        "num_units": 4,
                        "style": 2,
                        "tier_current": 2,
                        "tier_total": 3
                    }
                ],
                "units": [
                    {
                        "character_id": "TFT11_Jax",
                        "itemNames": [],
                        "name": "",
                        "rarity": 0,
                        "tier": 2
                    },
                    {
                        "character_id": "TFT11_Caitlyn",
                        "itemNames": [],
                        "name": "",
                        "rarity": 0,
                        "tier": 2
                    },
                    {
                        "character_id": "TFT11_Senna",
                        "itemNames": [],
                        "name": "",
                        "rarity": 1,
                        "tier": 2
                    },
                    {
                        "character_id": "TFT11_Illaoi",
                        "itemNames": [
                            "TFT_Item_SpectralGauntlet",
                            "TFT_Item_Leviathan",
                            "TFT_Item_RedBuff"
                        ],
                        "name": "",
                        "rarity": 2,
                        "tier": 2
                    },
                    {
                        "character_id": "TFT11_Amumu",
                        "itemNames": [
                            "TFT_Item_WarmogsArmor",
                            "TFT_Item_Redemption",
                            "TFT_Item_NightHarvester"
                        ],
                        "name": "",
                        "rarity": 2,
                        "tier": 3
                    },
                    {
                        "character_id": "TFT11_Aphelios",
                        "itemNames": [],
                        "name": "",
                        "rarity": 2,
                        "tier": 2
                    },
                    {
                        "character_id": "TFT11_Nautilus",
                        "itemNames": [],
                        "name": "",
                        "rarity": 4,
                        "tier": 1
                    },
                    {
                        "character_id": "TFT11_Ashe",
                        "itemNames": [
                            "TFT_Item_InfinityEdge",
                            "TFT_Item_HextechGunblade",
                            "TFT_Item_LastWhisper"
                        ],
                        "name": "",
                        "rarity": 4,
                        "tier": 2
                    }
                ]
            },
            {
                "augments": [
                    "TFT11_Augment_MythicCrest",
                    "TFT6_Augment_TinyTitans",
                    "TFT9_Augment_BigGrabBag"
                ],
                "companion": {
                    "content_ID": "ad464e8e-30f6-4ae9-8dc4-e198f040970c",
                    "item_ID": 7010,
                    "skin_ID": 10,
                    "species": "PetGemTiger"
                },
                "gold_left": 3,
                "last_round": 34,
                "level": 10,
                "missions": {
                    "PlayerScore2": 98
                },
                "placement": 5,
                "players_eliminated": 0,
                "puuid": "IqrC2L86g3O7fcWP3KBTEScZHJ42eJ-VvP--E8TY_FinN9gLnpqICExBByu_n1m1_meJ8s6skUTRcg",
                "time_eliminated": 1971.0093994140625,
                "total_damage_to_players": 81,
                "traits": [
                    {
                        "name": "TFT11_Arcanist",
                        "num_units": 1,
                        "style": 0,
                        "tier_current": 0,
                        "tier_total": 4
                    },
                    {
                        "name": "TFT11_Behemoth",
                        "num_units": 1,
                        "style": 0,
                        "tier_current": 0,
                        "tier_total": 3
                    },
                    {
                        "name": "TFT11_Bruiser",
                        "num_units": 1,
                        "style": 0,
                        "tier_current": 0,
                        "tier_total": 4
                    },
                    {
                        "name": "TFT11_Dragonlord",
                        "num_units": 1,
                        "style": 0,
                        "tier_current": 0,
                        "tier_total": 4
                    },
                    {
                        "name": "TFT11_Dryad",
                        "num_units": 1,
                        "style": 0,
                        "tier_current": 0,
                        "tier_total": 3
                    },
                    {
                        "name": "TFT11_Exalted",
                        "num_units": 2,
                        "style": 0,
                        "tier_current": 0,
                        "tier_total": 2
                    },
                    {
                        "name": "TFT11_Fortune",
                        "num_units": 1,
                        "style": 0,
                        "tier_current": 0,
                        "tier_total": 3
                    },
                    {
                        "name": "TFT11_Heavenly",
                        "num_units": 1,
                        "style": 0,
                        "tier_current": 0,
                        "tier_total": 6
                    },
                    {
                        "name": "TFT11_Invoker",
                        "num_units": 6,
                        "style": 3,
                        "tier_current": 3,
                        "tier_total": 3
                    },
                    {
                        "name": "TFT11_Mythic",
                        "num_units": 7,
                        "style": 3,
                        "tier_current": 3,
                        "tier_total": 4
                    },
                    {
                        "name": "TFT11_Sniper",
                        "num_units": 1,
                        "style": 0,
                        "tier_current": 0,
                        "tier_total": 3
                    },
                    {
                        "name": "TFT11_Trickshot",
                        "num_units": 1,
                        "style": 0,
                        "tier_current": 0,
                        "tier_total": 2
                    },
                    {
                        "name": "TFT11_Umbral",
                        "num_units": 1,
                        "style": 0,
                        "tier_current": 0,
                        "tier_total": 4
                    }
                ],
                "units": [
                    {
                        "character_id": "TFT11_KogMaw",
                        "itemNames": [],
                        "name": "",
                        "rarity": 0,
                        "tier": 2
                    },
                    {
                        "character_id": "TFT11_ChoGath",
                        "itemNames": [],
                        "name": "",
                        "rarity": 0,
                        "tier": 2
                    },
                    {
                        "character_id": "TFT11_Janna",
                        "itemNames": [],
                        "name": "",
                        "rarity": 1,
                        "tier": 2
                    },
                    {
                        "character_id": "TFT11_Neeko",
                        "itemNames": [],
                        "name": "",
                        "rarity": 1,
                        "tier": 2
                    },
                    {
                        "character_id": "TFT11_TahmKench",
                        "itemNames": [
                            "TFT_Item_NightHarvester",
                            "TFT_Item_BrambleVest"
                        ],
                        "name": "",
                        "rarity": 2,
                        "tier": 2
                    },
                    {
                        "character_id": "TFT11_Bard",
                        "itemNames": [
                            "TFT_Item_GuinsoosRageblade",
                            "TFT_Item_GuinsoosRageblade"
                        ],
                        "name": "",
                        "rarity": 2,
                        "tier": 2
                    },
                    {
                        "character_id": "TFT11_Alune",
                        "itemNames": [
                            "TFT11_Item_MythicEmblemItem"
                        ],
                        "name": "",
                        "rarity": 2,
                        "tier": 2
                    },
                    {
                        "character_id": "TFT11_Lillia",
                        "itemNames": [],
                        "name": "",
                        "rarity": 4,
                        "tier": 1
                    },
                    {
                        "character_id": "TFT11_Annie",
                        "itemNames": [
                            "TFT_Item_NightHarvester",
                            "TFT_Item_WarmogsArmor",
                            "TFT_Item_DragonsClaw"
                        ],
                        "name": "",
                        "rarity": 4,
                        "tier": 2
                    },
                    {
                        "character_id": "TFT11_Azir",
                        "itemNames": [
                            "TFT_Item_JeweledGauntlet",
                            "TFT_Item_HextechGunblade",
                            "TFT_Item_RabadonsDeathcap"
                        ],
                        "name": "",
                        "rarity": 6,
                        "tier": 1
                    }
                ]
            },
            {
                "augments": [
                    "TFT11_Augment_YorickCarry",
                    "TFT9_Augment_Formation1",
                    "TFT6_Augment_PortableForge"
                ],
                "companion": {
                    "content_ID": "fb7ee12f-21da-428d-9093-26b3801583bf",
                    "item_ID": 27030,
                    "skin_ID": 30,
                    "species": "PetChoncc"
                },
                "gold_left": 1,
                "last_round": 34,
                "level": 8,
                "missions": {
                    "PlayerScore2": 197
                },
                "placement": 4,
                "players_eliminated": 0,
                "puuid": "EOxDWPkVxvgjKJ1VBgvGgPMLyjbjH_9muNVdSnpq4OTztRIASrt1VmjPkl0PeASCfcquMsLbbzYnVA",
                "time_eliminated": 1971.110595703125,
                "total_damage_to_players": 107,
                "traits": [
                    {
                        "name": "TFT11_Behemoth",
                        "num_units": 1,
                        "style": 0,
                        "tier_current": 0,
                        "tier_total": 3
                    },
                    {
                        "name": "TFT11_Bruiser",
                        "num_units": 2,
                        "style": 1,
                        "tier_current": 1,
                        "tier_total": 4
                    },
                    {
                        "name": "TFT11_Duelist",
                        "num_units": 2,
                        "style": 1,
                        "tier_current": 1,
                        "tier_total": 4
                    },
                    {
                        "name": "TFT11_Exalted",
                        "num_units": 1,
                        "style": 0,
                        "tier_current": 0,
                        "tier_total": 2
                    },
                    {
                        "name": "TFT11_Fortune",
                        "num_units": 1,
                        "style": 0,
                        "tier_current": 0,
                        "tier_total": 3
                    },
                    {
                        "name": "TFT11_Ghostly",
                        "num_units": 1,
                        "style": 0,
                        "tier_current": 0,
                        "tier_total": 4
                    },
                    {
                        "name": "TFT11_InkShadow",
                        "num_units": 1,
                        "style": 0,
                        "tier_current": 0,
                        "tier_total": 3
                    },
                    {
                        "name": "TFT11_Invoker",
                        "num_units": 2,
                        "style": 1,
                        "tier_current": 1,
                        "tier_total": 3
                    },
                    {
                        "name": "TFT11_Reaper",
                        "num_units": 1,
                        "style": 0,
                        "tier_current": 0,
                        "tier_total": 2
                    },
                    {
                        "name": "TFT11_Storyweaver",
                        "num_units": 1,
                        "style": 0,
                        "tier_current": 0,
                        "tier_total": 4
                    },
                    {
                        "name": "TFT11_Umbral",
                        "num_units": 6,
                        "style": 3,
                        "tier_current": 3,
                        "tier_total": 4
                    }
                ],
                "units": [
                    {
                        "character_id": "TFT11_Darius",
                        "itemNames": [],
                        "name": "",
                        "rarity": 0,
                        "tier": 2
                    },
                    {
                        "character_id": "TFT11_Yorick",
                        "itemNames": [
                            "TFT_Item_Redemption"
                        ],
                        "name": "",
                        "rarity": 1,
                        "tier": 3
                    },
                    {
                        "character_id": "TFT11_Aatrox",
                        "itemNames": [],
                        "name": "",
                        "rarity": 1,
                        "tier": 1
                    },
                    {
                        "character_id": "TFT11_Yone",
                        "itemNames": [
                            "TFT_Item_Bloodthirster",
                            "TFT_Item_TitansResolve",
                            "TFT_Item_Artifact_Mittens"
                        ],
                        "name": "",
                        "rarity": 2,
                        "tier": 3
                    },
                    {
                        "character_id": "TFT11_Alune",
                        "itemNames": [
                            "TFT_Item_RapidFireCannon",
                            "TFT_Item_SpearOfShojin",
                            "TFT_Item_JeweledGauntlet"
                        ],
                        "name": "",
                        "rarity": 2,
                        "tier": 2
                    },
                    {
                        "character_id": "TFT11_Sylas",
                        "itemNames": [
                            "TFT_Item_Leviathan"
                        ],
                        "name": "",
                        "rarity": 4,
                        "tier": 2
                    },
                    {
                        "character_id": "TFT11_Annie",
                        "itemNames": [
                            "TFT_Item_Redemption"
                        ],
                        "name": "",
                        "rarity": 4,
                        "tier": 1
                    },
                    {
                        "character_id": "TFT11_Irelia",
                        "itemNames": [
                            "TFT11_Item_UmbralEmblemItem"
                        ],
                        "name": "",
                        "rarity": 6,
                        "tier": 1
                    }
                ]
            },
            {
                "augments": [
                    "TFT11_Augment_Dragonlord",
                    "TFT9_Augment_MissedConnections",
                    "TFT11_Augment_DynamicDuo"
                ],
                "companion": {
                    "content_ID": "f88f36bf-0797-452e-8ea2-cf1aef5f0421",
                    "item_ID": 23018,
                    "skin_ID": 18,
                    "species": "PetFairy"
                },
                "gold_left": 1,
                "last_round": 38,
                "level": 8,
                "missions": {
                    "PlayerScore2": 217
                },
                "placement": 2,
                "players_eliminated": 3,
                "puuid": "nePyy7qsdK0irJsw3eKwUUQc20aO7dT1xviOAKO0tbxe27kP2PdQ0HbLaEGT6rK-Ehe5OIM7ujhOCw",
                "time_eliminated": 2173.160400390625,
                "total_damage_to_players": 155,
                "traits": [
                    {
                        "name": "TFT11_Arcanist",
                        "num_units": 2,
                        "style": 1,
                        "tier_current": 1,
                        "tier_total": 4
                    },
                    {
                        "name": "TFT11_Behemoth",
                        "num_units": 2,
                        "style": 1,
                        "tier_current": 1,
                        "tier_total": 3
                    },
                    {
                        "name": "TFT11_Dryad",
                        "num_units": 4,
                        "style": 3,
                        "tier_current": 2,
                        "tier_total": 3
                    },
                    {
                        "name": "TFT11_Exalted",
                        "num_units": 1,
                        "style": 0,
                        "tier_current": 0,
                        "tier_total": 2
                    },
                    {
                        "name": "TFT11_Fated",
                        "num_units": 5,
                        "style": 2,
                        "tier_current": 2,
                        "tier_total": 4
                    },
                    {
                        "name": "TFT11_Fortune",
                        "num_units": 1,
                        "style": 0,
                        "tier_current": 0,
                        "tier_total": 3
                    },
                    {
                        "name": "TFT11_Invoker",
                        "num_units": 2,
                        "style": 1,
                        "tier_current": 1,
                        "tier_total": 3
                    },
                    {
                        "name": "TFT11_Reaper",
                        "num_units": 1,
                        "style": 0,
                        "tier_current": 0,
                        "tier_total": 2
                    },
                    {
                        "name": "TFT11_Warden",
                        "num_units": 1,
                        "style": 0,
                        "tier_current": 0,
                        "tier_total": 3
                    }
                ],
                "units": [
                    {
                        "character_id": "TFT11_Ahri",
                        "itemNames": [],
                        "name": "",
                        "rarity": 0,
                        "tier": 3
                    },
                    {
                        "character_id": "TFT11_Gnar",
                        "itemNames": [
                            "TFT11_Item_FatedEmblemItem"
                        ],
                        "name": "",
                        "rarity": 1,
                        "tier": 3
                    },
                    {
                        "character_id": "TFT11_Kindred",
                        "itemNames": [],
                        "name": "",
                        "rarity": 1,
                        "tier": 3
                    },
                    {
                        "character_id": "TFT11_Thresh",
                        "itemNames": [
                            "TFT_Item_ThiefsGloves",
                            "TFT_Item_GargoyleStoneplate",
                            "TFT_Item_RedBuff"
                        ],
                        "name": "",
                        "rarity": 2,
                        "tier": 3
                    },
                    {
                        "character_id": "TFT11_Syndra",
                        "itemNames": [
                            "TFT_Item_JeweledGauntlet",
                            "TFT_Item_Leviathan",
                            "TFT_Item_TearOfTheGoddess"
                        ],
                        "name": "",
                        "rarity": 4,
                        "tier": 2
                    },
                    {
                        "character_id": "TFT11_Ornn",
                        "itemNames": [
                            "TFT_Item_BrambleVest",
                            "TFT_Item_WarmogsArmor"
                        ],
                        "name": "",
                        "rarity": 4,
                        "tier": 2
                    },
                    {
                        "character_id": "TFT11_Annie",
                        "itemNames": [
                            "TFT_Item_BrambleVest",
                            "TFT_Item_WarmogsArmor",
                            "TFT_Item_GargoyleStoneplate"
                        ],
                        "name": "",
                        "rarity": 4,
                        "tier": 2
                    },
                    {
                        "character_id": "TFT11_Azir",
                        "itemNames": [
                            "TFT_Item_MadredsBloodrazor"
                        ],
                        "name": "",
                        "rarity": 6,
                        "tier": 2
                    }
                ]
            },
            {
                "augments": [
                    "TFT9_Augment_BuildingACollectionPlus",
                    "TFT9_Augment_YoungAndWildAndFree",
                    "TFT9_Augment_JeweledLotus"
                ],
                "companion": {
                    "content_ID": "d6a34cac-ff32-43bc-9c8d-d8a303169c29",
                    "item_ID": 31006,
                    "skin_ID": 6,
                    "species": "PetNimblefoot"
                },
                "gold_left": 1,
                "last_round": 35,
                "level": 7,
                "missions": {
                    "PlayerScore2": 203
                },
                "placement": 3,
                "players_eliminated": 0,
                "puuid": "6riTyikRSA7KuuFVS6fdpTzT_wkHz7ZVO2jXiob2D_S0bI54zkN6EJUb8b10ESMb-p2SUV4L73yd3g",
                "time_eliminated": 2029.8958740234375,
                "total_damage_to_players": 114,
                "traits": [
                    {
                        "name": "TFT11_Altruist",
                        "num_units": 1,
                        "style": 0,
                        "tier_current": 0,
                        "tier_total": 3
                    },
                    {
                        "name": "TFT11_Arcanist",
                        "num_units": 1,
                        "style": 0,
                        "tier_current": 0,
                        "tier_total": 4
                    },
                    {
                        "name": "TFT11_Bruiser",
                        "num_units": 2,
                        "style": 1,
                        "tier_current": 1,
                        "tier_total": 4
                    },
                    {
                        "name": "TFT11_Duelist",
                        "num_units": 1,
                        "style": 0,
                        "tier_current": 0,
                        "tier_total": 4
                    },
                    {
                        "name": "TFT11_Exalted",
                        "num_units": 1,
                        "style": 0,
                        "tier_current": 0,
                        "tier_total": 2
                    },
                    {
                        "name": "TFT11_Fortune",
                        "num_units": 1,
                        "style": 0,
                        "tier_current": 0,
                        "tier_total": 3
                    },
                    {
                        "name": "TFT11_Sage",
                        "num_units": 1,
                        "style": 0,
                        "tier_current": 0,
                        "tier_total": 4
                    },
                    {
                        "name": "TFT11_Storyweaver",
                        "num_units": 7,
                        "style": 3,
                        "tier_current": 3,
                        "tier_total": 4
                    },
                    {
                        "name": "TFT11_Trickshot",
                        "num_units": 1,
                        "style": 0,
                        "tier_current": 0,
                        "tier_total": 2
                    },
                    {
                        "name": "TFT11_Warden",
                        "num_units": 1,
                        "style": 0,
                        "tier_current": 0,
                        "tier_total": 3
                    }
                ],
                "units": [
                    {
                        "character_id": "TFT11_Sivir",
                        "itemNames": [
                            "TFT_Item_RapidFireCannon"
                        ],
                        "name": "",
                        "rarity": 0,
                        "tier": 2
                    },
                    {
                        "character_id": "TFT11_Garen",
                        "itemNames": [
                            "TFT_Item_GiantsBelt"
                        ],
                        "name": "",
                        "rarity": 0,
                        "tier": 2
                    },
                    {
                        "character_id": "TFT11_Zyra",
                        "itemNames": [
                            "TFT_Item_RabadonsDeathcap",
                            "TFT_Item_StatikkShiv",
                            "TFT_Item_SpearOfShojin"
                        ],
                        "name": "",
                        "rarity": 1,
                        "tier": 3
                    },
                    {
                        "character_id": "TFT11_Riven",
                        "itemNames": [],
                        "name": "",
                        "rarity": 1,
                        "tier": 2
                    },
                    {
                        "character_id": "TFT11_Zoe",
                        "itemNames": [
                            "TFT_Item_StatikkShiv",
                            "TFT_Item_JeweledGauntlet"
                        ],
                        "name": "",
                        "rarity": 2,
                        "tier": 2
                    },
                    {
                        "character_id": "TFT11_Galio",
                        "itemNames": [
                            "TFT_Item_NightHarvester",
                            "TFT_Item_Redemption",
                            "TFT_Item_DragonsClaw"
                        ],
                        "name": "",
                        "rarity": 4,
                        "tier": 2
                    },
                    {
                        "character_id": "TFT11_Irelia",
                        "itemNames": [
                            "TFT_Item_ThiefsGloves",
                            "TFT_Item_JeweledGauntlet",
                            "TFT_Item_RunaansHurricane"
                        ],
                        "name": "",
                        "rarity": 6,
                        "tier": 1
                    },
                    {
                        "character_id": "TFT11_Kayle",
                        "itemNames": [
                            "TFT11_Storyweaver7_AP",
                            "TFT11_Storyweaver5_AP",
                            "TFT11_Storyweaver3_Support"
                        ],
                        "name": "",
                        "rarity": 9,
                        "tier": 3
                    }
                ]
            }
        ],
        "queueId": 1100,
        "queue_id": 1100,
        "tft_game_type": "standard",
        "tft_set_core_name": "TFTSet11",
        "tft_set_number": 11
    }
}